[
  {
    "ContainingType": "Journey.Api.Controllers.TripsController",
    "Method": "Register",
    "RelativePath": "api/Trips",
    "HttpMethod": "POST",
    "IsController": true,
    "Order": 0,
    "Parameters": [
      {
        "Name": "request",
        "Type": "Journey.Communication.Requests.RequestRegisterTripJson",
        "IsRequired": true
      }
    ],
    "ReturnTypes": []
  },
  {
    "ContainingType": "Journey.Api.Controllers.TripsController",
    "Method": "GetAll",
    "RelativePath": "api/Trips",
    "HttpMethod": "GET",
    "IsController": true,
    "Order": 0,
    "Parameters": [],
    "ReturnTypes": []
  }
]